{"cameraMode":{"drawMode":0,"name":"Shaded","section":"Shading Mode"},"sceneLighting":true,"audioPlay":false,"sceneViewState":{"m_AlwaysRefresh":false,"showFog":true,"showSkybox":true,"showFlares":true,"showImageEffects":true,"showParticleSystems":true,"showVisualEffectGraphs":true,"m_FxEnabled":true},"in2DMode":false,"pivot":{"x":2.825688600540161,"y":5.0077433586120609,"z":-3.1780760288238527},"rotation":{"x":0.2140091061592102,"y":0.4682886302471161,"z":-0.11802719533443451,"w":0.8491057753562927},"size":0.2880186438560486,"orthographic":false}